snomed_neo4j_core/__init__.py
snomed_neo4j_core/asd.py
snomed_neo4j_core/client.py
snomed_neo4j_core/download.py
snomed_neo4j_core/loader.py
snomed_neo4j_core/logging.py
snomed_neo4j_core/models.py
snomed_neo4j_core/py.typed
snomed_neo4j_core/slim.py
snomed_neo4j_core/utils.py
snomed_neo4j_core-0.1.1.dist-info/METADATA
snomed_neo4j_core-0.1.1.dist-info/WHEEL
snomed_neo4j_core-0.1.1.dist-info/entry_points.txt
snomed_neo4j_core-0.1.1.dist-info/RECORD
