Metadata-Version: 2.4
Name: snomed-neo4j-core
Version: 0.1.1
Summary: Add your description here
Author-email: Bence Szabó <bszabo96@gmail.com>
Requires-Python: >=3.12
Requires-Dist: neo4j>=5.28.1
Requires-Dist: pydantic>=2.11.5
Requires-Dist: python-dotenv>=1.1.0
Requires-Dist: requests>=2.32.3
Requires-Dist: tqdm>=4.67.1
